{
    "observation.state": {
        "min": [
            180.615234375,
            67.8515625,
            191.953125,
            246.26953125,
            188.525390625,
            155.21484375
        ],
        "max": [
            198.10546875,
            185.9765625,
            279.404296875,
            268.76953125,
            245.478515625,
            179.384765625
        ],
        "mean": [
            190.75062561035156,
            120.29608154296875,
            240.16748046875,
            252.80397033691406,
            206.1350555419922,
            164.72019958496094
        ],
        "std": [
            6.36580228805542,
            42.4905891418457,
            29.879446029663086,
            4.008779525756836,
            19.333019256591797,
            8.068190574645996
        ],
        "count": [
            559
        ],
        "q01": [
            180.615234375,
            68.46798175506592,
            192.0472617340088,
            246.26953125,
            188.525390625,
            155.3022628166562
        ],
        "q10": [
            180.70594628516665,
            68.53759398460389,
            198.0934042123648,
            248.73009843092697,
            190.10390106201172,
            159.08638458251954
        ],
        "q50": [
            191.95365578787667,
            135.0792864631204,
            230.63530751278526,
            252.2491539403012,
            197.84114503860474,
            160.84049918434837
        ],
        "q90": [
            197.84215791490342,
            176.03974906073677,
            279.3926599775042,
            256.28664169311526,
            245.47180861623664,
            178.8565906270345
        ],
        "q99": [
            198.10449210357666,
            185.96455893776633,
            279.4031331852504,
            268.6811162567139,
            245.47784492412367,
            179.38347805204845
        ]
    },
    "action": {
        "min": [
            180.615234375,
            67.8515625,
            191.953125,
            246.26953125,
            278.525390625,
            155.21484375
        ],
        "max": [
            198.10546875,
            185.9765625,
            279.404296875,
            268.76953125,
            335.478515625,
            179.384765625
        ],
        "mean": [
            190.75062561035156,
            120.29608154296875,
            240.16748046875,
            252.80397033691406,
            296.13494873046875,
            164.72019958496094
        ],
        "std": [
            6.36580228805542,
            42.4905891418457,
            29.879446029663086,
            4.008779525756836,
            19.334836959838867,
            8.068190574645996
        ],
        "count": [
            559
        ],
        "q01": [
            180.615234375,
            68.46798175506592,
            192.0472617340088,
            246.26953125,
            278.525390625,
            155.3022628166562
        ],
        "q10": [
            180.70594628516665,
            68.53759398460389,
            198.0934042123648,
            248.73009843092697,
            280.10389221191406,
            159.08638458251954
        ],
        "q50": [
            191.95365578787667,
            135.0792864631204,
            230.63530751278526,
            252.2491539403012,
            287.8411474227905,
            160.84049918434837
        ],
        "q90": [
            197.84215791490342,
            176.03974906073677,
            279.3926599775042,
            256.28664169311526,
            335.47181759482936,
            178.8565906270345
        ],
        "q99": [
            198.10449210357666,
            185.96455893776633,
            279.4031331852504,
            268.6811162567139,
            335.47784582198295,
            179.38347805204845
        ]
    },
    "observation.images.side": {
        "min": [
            [
                [
                    0.0
                ]
            ],
            [
                [
                    0.0
                ]
            ],
            [
                [
                    0.0
                ]
            ]
        ],
        "max": [
            [
                [
                    1.0
                ]
            ],
            [
                [
                    1.0
                ]
            ],
            [
                [
                    1.0
                ]
            ]
        ],
        "mean": [
            [
                [
                    0.5392458129084967
                ]
            ],
            [
                [
                    0.5260849941950465
                ]
            ],
            [
                [
                    0.4997322644335512
                ]
            ]
        ],
        "std": [
            [
                [
                    0.0
                ]
            ],
            [
                [
                    0.0
                ]
            ],
            [
                [
                    0.0
                ]
            ]
        ],
        "count": [
            114
        ],
        "q01": [
            [
                [
                    -3.9215686274509807e-13
                ]
            ],
            [
                [
                    -3.9215686274509807e-13
                ]
            ],
            [
                [
                    0.01576140477876575
                ]
            ]
        ],
        "q10": [
            [
                [
                    0.11777634715353574
                ]
            ],
            [
                [
                    0.12152048343748291
                ]
            ],
            [
                [
                    0.1529882239099315
                ]
            ]
        ],
        "q50": [
            [
                [
                    0.6470025374424035
                ]
            ],
            [
                [
                    0.6274027880960663
                ]
            ],
            [
                [
                    0.5803531057114467
                ]
            ]
        ],
        "q90": [
            [
                [
                    0.7842095979095891
                ]
            ],
            [
                [
                    0.847030201607862
                ]
            ],
            [
                [
                    0.8901547042867953
                ]
            ]
        ],
        "q99": [
            [
                [
                    0.854894706168321
                ]
            ],
            [
                [
                    0.9018417172596386
                ]
            ],
            [
                [
                    0.9529642299506745
                ]
            ]
        ]
    },
    "observation.images.down": {
        "min": [
            [
                [
                    0.0
                ]
            ],
            [
                [
                    0.0
                ]
            ],
            [
                [
                    0.0
                ]
            ]
        ],
        "max": [
            [
                [
                    1.0
                ]
            ],
            [
                [
                    1.0
                ]
            ],
            [
                [
                    1.0
                ]
            ]
        ],
        "mean": [
            [
                [
                    0.5984973053548905
                ]
            ],
            [
                [
                    0.5698187797414288
                ]
            ],
            [
                [
                    0.550541781332416
                ]
            ]
        ],
        "std": [
            [
                [
                    0.0
                ]
            ],
            [
                [
                    0.0
                ]
            ],
            [
                [
                    0.0
                ]
            ]
        ],
        "count": [
            114
        ],
        "q01": [
            [
                [
                    0.031371850938961054
                ]
            ],
            [
                [
                    0.011761289809798941
                ]
            ],
            [
                [
                    -3.9215686274509807e-13
                ]
            ]
        ],
        "q10": [
            [
                [
                    0.14505300353329048
                ]
            ],
            [
                [
                    0.16061602002476508
                ]
            ],
            [
                [
                    0.1686270376687255
                ]
            ]
        ],
        "q50": [
            [
                [
                    0.6704751359283292
                ]
            ],
            [
                [
                    0.635266095798875
                ]
            ],
            [
                [
                    0.6157642433596878
                ]
            ]
        ],
        "q90": [
            [
                [
                    0.9019265672602157
                ]
            ],
            [
                [
                    0.8353032317638824
                ]
            ],
            [
                [
                    0.8822984126987123
                ]
            ]
        ],
        "q99": [
            [
                [
                    0.9998611343742024
                ]
            ],
            [
                [
                    0.9999498482023007
                ]
            ],
            [
                [
                    0.9999782700855228
                ]
            ]
        ]
    },
    "timestamp": {
        "min": [
            0.0
        ],
        "max": [
            18.6
        ],
        "mean": [
            9.299999999999999
        ],
        "std": [
            5.3789714010518175
        ],
        "count": [
            559
        ],
        "q01": [
            0.16587479990178355
        ],
        "q10": [
            1.8335879999197158
        ],
        "q50": [
            9.30186000000002
        ],
        "q90": [
            16.766412000080283
        ],
        "q99": [
            18.434125200098215
        ]
    },
    "frame_index": {
        "min": [
            0
        ],
        "max": [
            558
        ],
        "mean": [
            279.0
        ],
        "std": [
            161.36914203155447
        ],
        "count": [
            559
        ],
        "q01": [
            4.976243999901784
        ],
        "q10": [
            55.007639999919725
        ],
        "q50": [
            278.9442
        ],
        "q90": [
            502.9923600000804
        ],
        "q99": [
            553.0237560000982
        ]
    },
    "episode_index": {
        "min": [
            0
        ],
        "max": [
            0
        ],
        "mean": [
            0.0
        ],
        "std": [
            0.0
        ],
        "count": [
            559
        ],
        "q01": [
            3.9999999999994176e-16
        ],
        "q10": [
            3.999999999999417e-15
        ],
        "q50": [
            1.9999999999997088e-14
        ],
        "q90": [
            3.599999999999476e-14
        ],
        "q99": [
            3.9599999999994235e-14
        ]
    },
    "index": {
        "min": [
            0
        ],
        "max": [
            558
        ],
        "mean": [
            279.0
        ],
        "std": [
            161.36914203155447
        ],
        "count": [
            559
        ],
        "q01": [
            4.976243999901784
        ],
        "q10": [
            55.007639999919725
        ],
        "q50": [
            278.9442
        ],
        "q90": [
            502.9923600000804
        ],
        "q99": [
            553.0237560000982
        ]
    },
    "task_index": {
        "min": [
            0
        ],
        "max": [
            0
        ],
        "mean": [
            0.0
        ],
        "std": [
            0.0
        ],
        "count": [
            559
        ],
        "q01": [
            3.9999999999994176e-16
        ],
        "q10": [
            3.999999999999417e-15
        ],
        "q50": [
            1.9999999999997088e-14
        ],
        "q90": [
            3.599999999999476e-14
        ],
        "q99": [
            3.9599999999994235e-14
        ]
    }
}